conan_builder/__init__.py
conan_builder/builder.py
conan_builder/conanfile.py
conan_builder/targets/CameraCtrl.py.in
conan_builder/targets/MaxDS.py.in
conan_builder/targets/MaxME.py.in
conan_builder/targets/OpenCV.py.in
conan_builder/targets/OpenSSL.py.in
conan_builder/targets/Poco.py.in
conan_builder/targets/Protoc.py.in
conan_builder/targets/SipEngine.py.in
conan_builder/targets/StackEngine.py.in
conan_builder/targets/VirtualDevice.py.in
conan_builder/targets/abseil.py.in
conan_builder/targets/boringssl.py.in
conan_builder/targets/breakpad.py.in
conan_builder/targets/bzip2.py.in
conan_builder/targets/cairo.py.in
conan_builder/targets/disruptor.py.in
conan_builder/targets/dssamples.py.in
conan_builder/targets/expat.py.in
conan_builder/targets/ffmpeg.py.in
conan_builder/targets/ffmpeg_record.py.in
conan_builder/targets/freetype.py.in
conan_builder/targets/gflags.py.in
conan_builder/targets/googletest.py.in
conan_builder/targets/gpu_sdk.py.in
conan_builder/targets/h323plus.py.in
conan_builder/targets/harfbuzz.py.in
conan_builder/targets/hisiaac.py.in
conan_builder/targets/intel_media_sdk.py.in
conan_builder/targets/jsoncpp.py.in
conan_builder/targets/libcares.py.in
conan_builder/targets/libcpuinfo.py.in
conan_builder/targets/libcurl.py.in
conan_builder/targets/libdb.py.in
conan_builder/targets/libevent.py.in
conan_builder/targets/libfacesdk.py.in
conan_builder/targets/libfdk_aac.py.in
conan_builder/targets/libjpeg.py.in
conan_builder/targets/libks.py.in
conan_builder/targets/libmfx.py.in
conan_builder/targets/libmysqlconnectorc.py.in
conan_builder/targets/libne10.py.in
conan_builder/targets/libpcap.py.in
conan_builder/targets/libpng.py.in
conan_builder/targets/libqrencode.py.in
conan_builder/targets/libressl.py.in
conan_builder/targets/libsndfile.py.in
conan_builder/targets/libsofia_sip_ua_static.py.in
conan_builder/targets/libsrtp.py.in
conan_builder/targets/libtiff.py.in
conan_builder/targets/libvpx.py.in
conan_builder/targets/libx264.py.in
conan_builder-0.0.4.dist-info/LICENSE.txt
conan_builder-0.0.4.dist-info/METADATA
conan_builder-0.0.4.dist-info/WHEEL
conan_builder-0.0.4.dist-info/entry_points.txt
conan_builder-0.0.4.dist-info/top_level.txt
conan_builder-0.0.4.dist-info/RECORD
