Metadata-Version: 2.1
Name: conan-builder
Version: 0.0.4
Summary: just a wrapper of conan.
Home-page: https://conan.io
Author: TigerLau
Author-email: tigerliu1985@hotmail.com
Classifier: Programming Language :: Python :: 3
Classifier: License :: OSI Approved :: MIT License
Classifier: Operating System :: OS Independent
Requires-Python: >=3
License-File: LICENSE.txt
